dymos/__init__.py
dymos/_options.py
dymos/load_case.py
dymos/run_problem.py
dymos/examples/__init__.py
dymos/examples/plotting.py
dymos/examples/aircraft_steady_flight/__init__.py
dymos/examples/aircraft_steady_flight/aircraft_ode.py
dymos/examples/aircraft_steady_flight/dynamic_pressure_comp.py
dymos/examples/aircraft_steady_flight/mass_comp.py
dymos/examples/aircraft_steady_flight/range_rate_comp.py
dymos/examples/aircraft_steady_flight/steady_flight_path_angle_comp.py
dymos/examples/aircraft_steady_flight/true_airspeed_comp.py
dymos/examples/aircraft_steady_flight/aero/__init__.py
dymos/examples/aircraft_steady_flight/aero/aero_coef_comp.py
dymos/examples/aircraft_steady_flight/aero/aero_forces_comp.py
dymos/examples/aircraft_steady_flight/aero/aerodynamics_group.py
dymos/examples/aircraft_steady_flight/aero/crm_data.py
dymos/examples/aircraft_steady_flight/aero/interpND_aero_coef_comp.py
dymos/examples/aircraft_steady_flight/aero/data/CRM_aero_inputs.dat
dymos/examples/aircraft_steady_flight/aero/data/CRM_aero_outputs.dat
dymos/examples/aircraft_steady_flight/aero/test/__init__.py
dymos/examples/aircraft_steady_flight/aero/test/test_aero_coef_comp.py
dymos/examples/aircraft_steady_flight/aero/test/test_interpND_aero_coef_comp.py
dymos/examples/aircraft_steady_flight/flight_equlibrium/__init__.py
dymos/examples/aircraft_steady_flight/flight_equlibrium/lift_equilibrium_comp.py
dymos/examples/aircraft_steady_flight/flight_equlibrium/steady_flight_equilibrium_group.py
dymos/examples/aircraft_steady_flight/flight_equlibrium/thrust_equilibrium_comp.py
dymos/examples/aircraft_steady_flight/flight_equlibrium/test/__init__.py
dymos/examples/aircraft_steady_flight/flight_equlibrium/test/test_flight_equilibrium_group.py
dymos/examples/aircraft_steady_flight/propulsion/__init__.py
dymos/examples/aircraft_steady_flight/propulsion/fuel_burn_rate_comp.py
dymos/examples/aircraft_steady_flight/propulsion/max_thrust_comp.py
dymos-1.15.0.dist-info/METADATA
dymos-1.15.0.dist-info/WHEEL
dymos-1.15.0.dist-info/entry_points.txt
dymos-1.15.0.dist-info/licenses/LICENSE
dymos-1.15.0.dist-info/RECORD
