Metadata-Version: 2.4
Name: dymos
Version: 1.15.0
Summary: Open-Source Optimization of Dynamic Multidisciplinary Systems
Project-URL: Homepage, https://github.com/OpenMDAO/dymos
License-Expression: Apache-2.0
License-File: LICENSE
Classifier: Development Status :: 5 - Production/Stable
Classifier: Intended Audience :: Science/Research
Classifier: License :: OSI Approved :: Apache Software License
Classifier: Natural Language :: English
Classifier: Operating System :: MacOS :: MacOS X
Classifier: Operating System :: Microsoft :: Windows
Classifier: Operating System :: POSIX :: Linux
Classifier: Programming Language :: Python
Classifier: Programming Language :: Python :: 3
Classifier: Programming Language :: Python :: Implementation :: CPython
Classifier: Topic :: Scientific/Engineering
Requires-Python: >=3.9
Requires-Dist: numpy
Requires-Dist: openmdao>=3.36.0
Requires-Dist: scipy>=1.11
Provides-Extra: all
Requires-Dist: aiounittest; extra == 'all'
Requires-Dist: bokeh; extra == 'all'
Requires-Dist: ipython; extra == 'all'
Requires-Dist: jax; extra == 'all'
Requires-Dist: jaxlib; extra == 'all'
Requires-Dist: jupyter; extra == 'all'
Requires-Dist: jupyter-book; extra == 'all'
Requires-Dist: matplotlib; extra == 'all'
Requires-Dist: nbconvert; extra == 'all'
Requires-Dist: notebook; extra == 'all'
Requires-Dist: numba; extra == 'all'
Requires-Dist: numpydoc>=1.1; extra == 'all'
Requires-Dist: packaging; extra == 'all'
Requires-Dist: playwright>=1.20; extra == 'all'
Requires-Dist: pre-commit; extra == 'all'
Requires-Dist: pycodestyle; extra == 'all'
Requires-Dist: redbaron; extra == 'all'
Requires-Dist: tabulate; extra == 'all'
Requires-Dist: testflo>=1.3.6; extra == 'all'
Provides-Extra: docs
Requires-Dist: bokeh; extra == 'docs'
Requires-Dist: ipython; extra == 'docs'
Requires-Dist: jax; extra == 'docs'
Requires-Dist: jaxlib; extra == 'docs'
Requires-Dist: jupyter; extra == 'docs'
Requires-Dist: jupyter-book; extra == 'docs'
Requires-Dist: matplotlib; extra == 'docs'
Requires-Dist: nbconvert; extra == 'docs'
Requires-Dist: notebook; extra == 'docs'
Requires-Dist: numpydoc>=1.1; extra == 'docs'
Requires-Dist: redbaron; extra == 'docs'
Requires-Dist: tabulate; extra == 'docs'
Provides-Extra: notebooks
Requires-Dist: ipython; extra == 'notebooks'
Requires-Dist: notebook; extra == 'notebooks'
Requires-Dist: tabulate; extra == 'notebooks'
Provides-Extra: numba
Requires-Dist: numba; extra == 'numba'
Provides-Extra: test
Requires-Dist: aiounittest; extra == 'test'
Requires-Dist: matplotlib; extra == 'test'
Requires-Dist: numpydoc>=1.1; extra == 'test'
Requires-Dist: packaging; extra == 'test'
Requires-Dist: playwright>=1.20; extra == 'test'
Requires-Dist: pre-commit; extra == 'test'
Requires-Dist: pycodestyle; extra == 'test'
Requires-Dist: testflo>=1.3.6; extra == 'test'
